SmoothAPI/__init__.py
SmoothAPI/chain.py
SmoothAPI/proxy_handlers.py
SmoothAPI/smoothapi.py
SmoothAPI-1.0.3.dist-info/LICENSE
SmoothAPI-1.0.3.dist-info/METADATA
SmoothAPI-1.0.3.dist-info/WHEEL
SmoothAPI-1.0.3.dist-info/top_level.txt
SmoothAPI-1.0.3.dist-info/RECORD
