Metadata-Version: 2.1
Name: SmoothAPI
Version: 1.0.3
Summary: An API Wrapper For Every API
Home-page: https://github.com/technerium/SmoothAPI
Author: Technerium
Author-email: technerium@gmail.com
License: MIT
Platform: UNKNOWN
Classifier: Programming Language :: Python :: 3
Classifier: License :: OSI Approved :: MIT License
Classifier: Operating System :: OS Independent
Requires-Dist: requests
